mcp_log_analyzer/__init__.py
mcp_log_analyzer/cli.py
mcp_log_analyzer/log_parser.py
mcp_log_analyzer/mcp_server.py
mcp_log_analyzer-0.1.2.dist-info/METADATA
mcp_log_analyzer-0.1.2.dist-info/WHEEL
mcp_log_analyzer-0.1.2.dist-info/entry_points.txt
mcp_log_analyzer-0.1.2.dist-info/RECORD
