Metadata-Version: 2.4
Name: mcp-log-analyzer
Version: 0.1.2
Summary: MCP服务器用于读取和解析日志文件
Project-URL: Homepage, https://github.com/your-username/mcp-log-analyzer
Project-URL: Repository, https://github.com/your-username/mcp-log-analyzer.git
Project-URL: Issues, https://github.com/your-username/mcp-log-analyzer/issues
Author: Log Analyzer Team
License: MIT
Keywords: analyzer,log,mcp,parser
Classifier: Development Status :: 4 - Beta
Classifier: Intended Audience :: Developers
Classifier: License :: OSI Approved :: MIT License
Classifier: Programming Language :: Python :: 3
Classifier: Programming Language :: Python :: 3.8
Classifier: Programming Language :: Python :: 3.9
Classifier: Programming Language :: Python :: 3.10
Classifier: Programming Language :: Python :: 3.11
Classifier: Programming Language :: Python :: 3.12
Requires-Python: >=3.8
Requires-Dist: fastmcp>=0.1.0
Provides-Extra: dev
Requires-Dist: black>=23.0; extra == 'dev'
Requires-Dist: flake8>=6.0; extra == 'dev'
Requires-Dist: isort>=5.0; extra == 'dev'
Requires-Dist: pytest-cov>=4.0; extra == 'dev'
Requires-Dist: pytest>=7.0; extra == 'dev'
